axion_hdl/README.md
axion_hdl/__init__.py
axion_hdl/address_manager.py
axion_hdl/annotation_parser.py
axion_hdl/axion.py
axion_hdl/bit_field_manager.py
axion_hdl/cli.py
axion_hdl/code_formatter.py
axion_hdl/doc_generators.py
axion_hdl/generator.py
axion_hdl/gui.py
axion_hdl/json_input_parser.py
axion_hdl/parser.py
axion_hdl/rule_checker.py
axion_hdl/source_modifier.py
axion_hdl/vhdl_utils.py
axion_hdl/xml_input_parser.py
axion_hdl/yaml_input_parser.py
axion_hdl/static/css/gui.css
axion_hdl/static/css/mac_terminal.css
axion_hdl/static/css/segmented_control.css
axion_hdl/static/css/style.css
axion_hdl/static/css/modules/config.css
axion_hdl/static/css/modules/diff.css
axion_hdl/static/css/modules/editor.css
axion_hdl/static/css/modules/generate.css
axion_hdl/static/css/modules/index.css
axion_hdl/static/css/modules/rule_check.css
axion_hdl/static/css/modules/source_viewer.css
axion_hdl/static/js/gui.js
axion_hdl/static/js/script.js
axion_hdl/static/js/modules/config.js
axion_hdl/static/js/modules/diff.js
axion_hdl/static/js/modules/editor.js
axion_hdl/static/js/modules/generate.js
axion_hdl/static/js/modules/index.js
axion_hdl/static/js/modules/rule_check.js
axion_hdl/static/js/modules/source_viewer.js
axion_hdl/templates/base.html
axion_hdl/templates/config.html
axion_hdl/templates/diff.html
axion_hdl/templates/editor.html
axion_hdl/templates/generate.html
axion_hdl/templates/index.html
axion_hdl/templates/rule_check.html
axion_hdl/templates/source_viewer.html
axion_hdl/templates/components/activity_log.html
axion_hdl-1.0.1.dist-info/licenses/LICENSE
axion_hdl-1.0.1.dist-info/METADATA
axion_hdl-1.0.1.dist-info/WHEEL
axion_hdl-1.0.1.dist-info/entry_points.txt
axion_hdl-1.0.1.dist-info/top_level.txt
axion_hdl-1.0.1.dist-info/RECORD
