Metadata-Version: 2.4
Name: axion-hdl
Version: 1.0.1
Summary: Automated AXI4-Lite Register Interface Generator for VHDL modules
Home-page: https://github.com/bugratufan/axion-hdl
Author: Bugra Tufan
Author-email: Bugra Tufan <bugratufan97@gmail.com>
Maintainer-email: Bugra Tufan <bugratufan97@gmail.com>
License: MIT
Project-URL: Homepage, https://github.com/bugratufan/axion-hdl
Project-URL: Documentation, https://github.com/bugratufan/axion-hdl/tree/main/docs
Project-URL: Repository, https://github.com/bugratufan/axion-hdl
Project-URL: Bug Tracker, https://github.com/bugratufan/axion-hdl/issues
Keywords: vhdl,axi,axi4-lite,fpga,hdl,register,generator,hardware,eda,rtl,code-generation,automation
Classifier: Development Status :: 5 - Production/Stable
Classifier: Intended Audience :: Developers
Classifier: Intended Audience :: Science/Research
Classifier: Topic :: Scientific/Engineering :: Electronic Design Automation (EDA)
Classifier: Topic :: Software Development :: Code Generators
Classifier: Programming Language :: Python :: 3
Classifier: Programming Language :: Python :: 3.7
Classifier: Programming Language :: Python :: 3.8
Classifier: Programming Language :: Python :: 3.9
Classifier: Programming Language :: Python :: 3.10
Classifier: Programming Language :: Python :: 3.11
Classifier: Programming Language :: Python :: 3.12
Classifier: Programming Language :: Python :: 3.13
Classifier: Operating System :: OS Independent
Classifier: Environment :: Console
Classifier: Natural Language :: English
Requires-Python: >=3.7
License-File: LICENSE
Requires-Dist: PyYAML>=6.0
Provides-Extra: gui
Requires-Dist: flask>=2.0; extra == "gui"
Requires-Dist: watchdog>=2.0; extra == "gui"
Provides-Extra: dev
Requires-Dist: pytest>=7.0; extra == "dev"
Requires-Dist: pytest-cov>=2.0; extra == "dev"
Requires-Dist: pytest-playwright>=0.4.0; extra == "dev"
Requires-Dist: pytest-xdist>=3.0; extra == "dev"
Requires-Dist: pytest-rerunfailures>=10.0; extra == "dev"
Requires-Dist: playwright>=1.40.0; extra == "dev"
Requires-Dist: black>=21.0; extra == "dev"
Requires-Dist: flake8>=3.9; extra == "dev"
Requires-Dist: build>=0.7; extra == "dev"
Requires-Dist: twine>=3.4; extra == "dev"
Requires-Dist: flask>=2.0; extra == "dev"
Requires-Dist: watchdog>=2.0; extra == "dev"
Requires-Dist: cocotb>=1.9.0; extra == "dev"
Requires-Dist: cocotb-bus>=0.2.1; extra == "dev"
Requires-Dist: cocotbext-axi>=0.1.24; extra == "dev"
Provides-Extra: vhdl-test
Requires-Dist: cocotb>=1.9.0; extra == "vhdl-test"
Requires-Dist: cocotb-bus>=0.2.1; extra == "vhdl-test"
Requires-Dist: cocotbext-axi>=0.1.24; extra == "vhdl-test"
Provides-Extra: docs
Requires-Dist: sphinx>=7.0; extra == "docs"
Requires-Dist: sphinx-rtd-theme>=2.0; extra == "docs"
Requires-Dist: myst-parser>=2.0; extra == "docs"
Dynamic: author
Dynamic: home-page
Dynamic: license-file
Dynamic: requires-python
